Workbook
Name CategoryList: Employees!$M$4:$M$9

Sheet Income Statement
A1: Intern Corp, Inc
A2: 2026 Financial Model
C4: 46023 | D4: =EOMONTH(C4,1) -> 46081 | E4: =EOMONTH(D4,1) -> 46112 | F4: =EOMONTH(E4,1) -> 46142 | G4: =EOMONTH(F4,1) -> 46173 | H4: =EOMONTH(G4,1) -> 46203 | I4: =EOMONTH(H4,1) -> 46234 | J4: =EOMONTH(I4,1) -> 46265 | K4: =EOMONTH(J4,1) -> 46295 | ... N4: =EOMONTH(M4,1) -> 46387 | P4: Total
B5: Revenue
B6: Software Revenue | C6: ='Revenue Build'!C19 -> 392000 | D6: ='Revenue Build'!D19 -> 468000 | E6: ='Revenue Build'!E19 -> 635200 | F6: ='Revenue Build'!F19 -> 696008 | G6: ='Revenue Build'!G19 -> 784424.08 | H6: ='Revenue Build'!H19 -> 921708.84 | I6: ='Revenue Build'!I19 -> 1025872 | J6: ='Revenue Build'!J19 -> 1125780.6 | ... N6: ='Revenue Build'!N19 -> 1661727.9 | P6: =SUM(C6:N6) -> 11863256
B7: Professional Services Revenue | C7: ='Revenue Build'!C25 -> 0 | D7: ='Revenue Build'!D25 -> 0 | E7: ='Revenue Build'!E25 -> 10609 | F7: ='Revenue Build'!F25 -> 10927.27 | G7: ='Revenue Build'!G25 -> 11255.088 | H7: ='Revenue Build'!H25 -> 16882.632 | I7: ='Revenue Build'!I25 -> 16882.632 | J7: ='Revenue Build'!J25 -> 16882.632 | ... N7: ='Revenue Build'!N25 -> 28137.72 | P7: =SUM(C7:N7) -> 179107.5
B8: Total Revenue | C8: =SUM(C6:C7) -> 392000 | D8: =SUM(D6:D7) -> 468000 | E8: =SUM(E6:E7) -> 645809 | F8: =SUM(F6:F7) -> 706935.27 | G8: =SUM(G6:G7) -> 795679.17 | H8: =SUM(H6:H7) -> 938591.47 | I8: =SUM(I6:I7) -> 1042754.6 | J8: =SUM(J6:J7) -> 1142663.3 | ... N8: =SUM(N6:N7) -> 1689865.6 | P8: =SUM(P6:P7) -> 12042364
B10: Cost of Sales
B11: Cost of Sales - Software | C11: =(SUMIF(Employees!$B:$B,'Income Statement'!$B11,Employees!$G:$G)/12)+(SUMIF('Other Expenses'!$B:$B,'Income Statement'!$B11,'Other Expenses'!$E:$E)/12) -> 111846.67 | D11: =(SUMIF(Employees!$B:$B,'Income Statement'!$B11,Employees!$G:$G)/12)+(SUMIF('Other Expenses'!$B:$B,'Income Statement'!$B11,'Other Expenses'!$E:$E)/12) -> 111846.67 | E11: =(SUMIF(Employees!$B:$B,'Income Statement'!$B11,Employees!$G:$G)/12)+(SUMIF('Other Expenses'!$B:$B,'Income Statement'!$B11,'Other Expenses'!$E:$E)/12) -> 111846.67 | F11: =(SUMIF(Employees!$B:$B,'Income Statement'!$B11,Employees!$G:$G)/12)+(SUMIF('Other Expenses'!$B:$B,'Income Statement'!$B11,'Other Expenses'!$E:$E)/12) -> 111846.67 | G11: =(SUMIF(Employees!$B:$B,'Income Statement'!$B11,Employees!$G:$G)/12)+(SUMIF('Other Expenses'!$B:$B,'Income Statement'!$B11,'Other Expenses'!$E:$E)/12) -> 111846.67 | H11: =(SUMIF(Employees!$B:$B,'Income Statement'!$B11,Employees!$G:$G)/12)+(SUMIF('Other Expenses'!$B:$B,'Income Statement'!$B11,'Other Expenses'!$E:$E)/12) -> 111846.67 | I11: =(SUMIF(Employees!$B:$B,'Income Statement'!$B11,Employees!$G:$G)/12)+(SUMIF('Other Expenses'!$B:$B,'Income Statement'!$B11,'Other Expenses'!$E:$E)/12) -> 111846.67 | J11: =(SUMIF(Employees!$B:$B,'Income Statement'!$B11,Employees!$G:$G)/12)+(SUMIF('Other Expenses'!$B:$B,'Income Statement'!$B11,'Other Expenses'!$E:$E)/12) -> 111846.67 | ... N11: =(SUMIF(Employees!$B:$B,'Income Statement'!$B11,Employees!$G:$G)/12)+(SUMIF('Other Expenses'!$B:$B,'Income Statement'!$B11,'Other Expenses'!$E:$E)/12) -> 111846.67 | P11: =SUM(C11:N11) -> 1342160
B12: Cost of Sales - Services | C12: =(SUMIF(Employees!$B:$B,'Income Statement'!$B12,Employees!$G:$G)/12)+(SUMIF('Other Expenses'!$B:$B,'Income Statement'!$B12,'Other Expenses'!$E:$E)/12) -> 80799.167 | D12: =(SUMIF(Employees!$B:$B,'Income Statement'!$B12,Employees!$G:$G)/12)+(SUMIF('Other Expenses'!$B:$B,'Income Statement'!$B12,'Other Expenses'!$E:$E)/12) -> 80799.167 | E12: =(SUMIF(Employees!$B:$B,'Income Statement'!$B12,Employees!$G:$G)/12)+(SUMIF('Other Expenses'!$B:$B,'Income Statement'!$B12,'Other Expenses'!$E:$E)/12) -> 80799.167 | F12: =(SUMIF(Employees!$B:$B,'Income Statement'!$B12,Employees!$G:$G)/12)+(SUMIF('Other Expenses'!$B:$B,'Income Statement'!$B12,'Other Expenses'!$E:$E)/12) -> 80799.167 | G12: =(SUMIF(Employees!$B:$B,'Income Statement'!$B12,Employees!$G:$G)/12)+(SUMIF('Other Expenses'!$B:$B,'Income Statement'!$B12,'Other Expenses'!$E:$E)/12) -> 80799.167 | H12: =(SUMIF(Employees!$B:$B,'Income Statement'!$B12,Employees!$G:$G)/12)+(SUMIF('Other Expenses'!$B:$B,'Income Statement'!$B12,'Other Expenses'!$E:$E)/12) -> 80799.167 | I12: =(SUMIF(Employees!$B:$B,'Income Statement'!$B12,Employees!$G:$G)/12)+(SUMIF('Other Expenses'!$B:$B,'Income Statement'!$B12,'Other Expenses'!$E:$E)/12) -> 80799.167 | J12: =(SUMIF(Employees!$B:$B,'Income Statement'!$B12,Employees!$G:$G)/12)+(SUMIF('Other Expenses'!$B:$B,'Income Statement'!$B12,'Other Expenses'!$E:$E)/12) -> 80799.167 | ... N12: =(SUMIF(Employees!$B:$B,'Income Statement'!$B12,Employees!$G:$G)/12)+(SUMIF('Other Expenses'!$B:$B,'Income Statement'!$B12,'Other Expenses'!$E:$E)/12) -> 80799.167 | P12: =SUM(C12:N12) -> 969590
B13: Total Cost of Sales | C13: =SUM(C11:C12) -> 192645.83 | D13: =SUM(D11:D12) -> 192645.83 | E13: =SUM(E11:E12) -> 192645.83 | F13: =SUM(F11:F12) -> 192645.83 | G13: =SUM(G11:G12) -> 192645.83 | H13: =SUM(H11:H12) -> 192645.83 | I13: =SUM(I11:I12) -> 192645.83 | J13: =SUM(J11:J12) -> 192645.83 | ... N13: =SUM(N11:N12) -> 192645.83 | P13: =SUM(P11:P12) -> 2311750
B15: Software Margin | C15: =C6-C11 -> 280153.33 | D15: =D6-D11 -> 356153.33 | E15: =E6-E11 -> 523353.33 | F15: =F6-F11 -> 584161.33 | G15: =G6-G11 -> 672577.41 | H15: =H6-H11 -> 809862.18 | I15: =I6-I11 -> 914025.31 | J15: =J6-J11 -> 1013934 | ... N15: =N6-N11 -> 1549881.2 | P15: =SUM(C15:N15) -> 10521096
B16: % | C16: =IFERROR(C15/C6,"n/a") -> 0.71467687 | D16: =IFERROR(D15/D6,"n/a") -> 0.7610114 | E16: =IFERROR(E15/E6,"n/a") -> 0.82391898 | F16: =IFERROR(F15/F6,"n/a") -> 0.83930261 | G16: =IFERROR(G15/G6,"n/a") -> 0.85741556 | H16: =IFERROR(H15/H6,"n/a") -> 0.87865293 | I16: =IFERROR(I15/I6,"n/a") -> 0.89097405 | J16: =IFERROR(J15/J6,"n/a") -> 0.90064968 | ... N16: =IFERROR(N15/N6,"n/a") -> 0.93269255 | P16: =IFERROR(P15/P6,"n/a") -> 0.88686411
B17: Services Margin | C17: =C7-C12 -> -80799.167 | D17: =D7-D12 -> -80799.167 | E17: =E7-E12 -> -70190.167 | F17: =F7-F12 -> -69871.897 | G17: =G7-G12 -> -69544.079 | H17: =H7-H12 -> -63916.535 | I17: =I7-I12 -> -63916.535 | J17: =J7-J12 -> -63916.535 | ... N17: =N7-N12 -> -52661.446 | P17: =SUM(C17:N17) -> -790482.5
B18: % | C18: =IFERROR(C17/C7,"n/a") -> n/a | D18: =IFERROR(D17/D7,"n/a") -> n/a | E18: =IFERROR(E17/E7,"n/a") -> -6.6160964 | F18: =IFERROR(F17/F7,"n/a") -> -6.3942683 | G18: =IFERROR(G17/G7,"n/a") -> -6.1789013 | H18: =IFERROR(H17/H7,"n/a") -> -3.7859342 | I18: =IFERROR(I17/I7,"n/a") -> -3.7859342 | J18: =IFERROR(J17/J7,"n/a") -> -3.7859342 | ... N18: =IFERROR(N17/N7,"n/a") -> -1.8715605 | P18: =IFERROR(P17/P7,"n/a") -> -4.4134527
B19: Gross Margin | C19: =C8-C13 -> 199354.17 | D19: =D8-D13 -> 275354.17 | E19: =E8-E13 -> 453163.17 | F19: =F8-F13 -> 514289.44 | G19: =G8-G13 -> 603033.33 | H19: =H8-H13 -> 745945.64 | I19: =I8-I13 -> 850108.78 | J19: =J8-J13 -> 950017.44 | ... N19: =N8-N13 -> 1497219.8 | P19: =SUM(C19:N19) -> 9730613.6
B22: Operating Expenses
B23: Sales | C23: =(SUMIF(Employees!$B:$B,'Income Statement'!$B23,Employees!$G:$G)/12)+(SUMIF('Other Expenses'!$B:$B,'Income Statement'!$B23,'Other Expenses'!$E:$E)/12) -> 83087.5 | D23: =(SUMIF(Employees!$B:$B,'Income Statement'!$B23,Employees!$G:$G)/12)+(SUMIF('Other Expenses'!$B:$B,'Income Statement'!$B23,'Other Expenses'!$E:$E)/12) -> 83087.5 | E23: =(SUMIF(Employees!$B:$B,'Income Statement'!$B23,Employees!$G:$G)/12)+(SUMIF('Other Expenses'!$B:$B,'Income Statement'!$B23,'Other Expenses'!$E:$E)/12) -> 83087.5 | F23: =(SUMIF(Employees!$B:$B,'Income Statement'!$B23,Employees!$G:$G)/12)+(SUMIF('Other Expenses'!$B:$B,'Income Statement'!$B23,'Other Expenses'!$E:$E)/12) -> 83087.5 | G23: =(SUMIF(Employees!$B:$B,'Income Statement'!$B23,Employees!$G:$G)/12)+(SUMIF('Other Expenses'!$B:$B,'Income Statement'!$B23,'Other Expenses'!$E:$E)/12) -> 83087.5 | H23: =(SUMIF(Employees!$B:$B,'Income Statement'!$B23,Employees!$G:$G)/12)+(SUMIF('Other Expenses'!$B:$B,'Income Statement'!$B23,'Other Expenses'!$E:$E)/12) -> 83087.5 | I23: =(SUMIF(Employees!$B:$B,'Income Statement'!$B23,Employees!$G:$G)/12)+(SUMIF('Other Expenses'!$B:$B,'Income Statement'!$B23,'Other Expenses'!$E:$E)/12) -> 83087.5 | J23: =(SUMIF(Employees!$B:$B,'Income Statement'!$B23,Employees!$G:$G)/12)+(SUMIF('Other Expenses'!$B:$B,'Income Statement'!$B23,'Other Expenses'!$E:$E)/12) -> 83087.5 | ... N23: =(SUMIF(Employees!$B:$B,'Income Statement'!$B23,Employees!$G:$G)/12)+(SUMIF('Other Expenses'!$B:$B,'Income Statement'!$B23,'Other Expenses'!$E:$E)/12) -> 83087.5 | P23: =SUM(C23:N23) -> 997050
B24: Marketing | C24: =(SUMIF(Employees!$B:$B,'Income Statement'!$B24,Employees!$G:$G)/12)+(SUMIF('Other Expenses'!$B:$B,'Income Statement'!$B24,'Other Expenses'!$E:$E)/12) -> 80125 | D24: =(SUMIF(Employees!$B:$B,'Income Statement'!$B24,Employees!$G:$G)/12)+(SUMIF('Other Expenses'!$B:$B,'Income Statement'!$B24,'Other Expenses'!$E:$E)/12) -> 80125 | E24: =(SUMIF(Employees!$B:$B,'Income Statement'!$B24,Employees!$G:$G)/12)+(SUMIF('Other Expenses'!$B:$B,'Income Statement'!$B24,'Other Expenses'!$E:$E)/12) -> 80125 | F24: =(SUMIF(Employees!$B:$B,'Income Statement'!$B24,Employees!$G:$G)/12)+(SUMIF('Other Expenses'!$B:$B,'Income Statement'!$B24,'Other Expenses'!$E:$E)/12) -> 80125 | G24: =(SUMIF(Employees!$B:$B,'Income Statement'!$B24,Employees!$G:$G)/12)+(SUMIF('Other Expenses'!$B:$B,'Income Statement'!$B24,'Other Expenses'!$E:$E)/12) -> 80125 | H24: =(SUMIF(Employees!$B:$B,'Income Statement'!$B24,Employees!$G:$G)/12)+(SUMIF('Other Expenses'!$B:$B,'Income Statement'!$B24,'Other Expenses'!$E:$E)/12) -> 80125 | I24: =(SUMIF(Employees!$B:$B,'Income Statement'!$B24,Employees!$G:$G)/12)+(SUMIF('Other Expenses'!$B:$B,'Income Statement'!$B24,'Other Expenses'!$E:$E)/12) -> 80125 | J24: =(SUMIF(Employees!$B:$B,'Income Statement'!$B24,Employees!$G:$G)/12)+(SUMIF('Other Expenses'!$B:$B,'Income Statement'!$B24,'Other Expenses'!$E:$E)/12) -> 80125 | ... N24: =(SUMIF(Employees!$B:$B,'Income Statement'!$B24,Employees!$G:$G)/12)+(SUMIF('Other Expenses'!$B:$B,'Income Statement'!$B24,'Other Expenses'!$E:$E)/12) -> 80125 | P24: =SUM(C24:N24) -> 961500
B25: Engineering and Product | C25: =(SUMIF(Employees!$B:$B,'Income Statement'!$B25,Employees!$G:$G)/12)+(SUMIF('Other Expenses'!$B:$B,'Income Statement'!$B25,'Other Expenses'!$E:$E)/12) -> 130814.17 | D25: =(SUMIF(Employees!$B:$B,'Income Statement'!$B25,Employees!$G:$G)/12)+(SUMIF('Other Expenses'!$B:$B,'Income Statement'!$B25,'Other Expenses'!$E:$E)/12) -> 130814.17 | E25: =(SUMIF(Employees!$B:$B,'Income Statement'!$B25,Employees!$G:$G)/12)+(SUMIF('Other Expenses'!$B:$B,'Income Statement'!$B25,'Other Expenses'!$E:$E)/12) -> 130814.17 | F25: =(SUMIF(Employees!$B:$B,'Income Statement'!$B25,Employees!$G:$G)/12)+(SUMIF('Other Expenses'!$B:$B,'Income Statement'!$B25,'Other Expenses'!$E:$E)/12) -> 130814.17 | G25: =(SUMIF(Employees!$B:$B,'Income Statement'!$B25,Employees!$G:$G)/12)+(SUMIF('Other Expenses'!$B:$B,'Income Statement'!$B25,'Other Expenses'!$E:$E)/12) -> 130814.17 | H25: =(SUMIF(Employees!$B:$B,'Income Statement'!$B25,Employees!$G:$G)/12)+(SUMIF('Other Expenses'!$B:$B,'Income Statement'!$B25,'Other Expenses'!$E:$E)/12) -> 130814.17 | I25: =(SUMIF(Employees!$B:$B,'Income Statement'!$B25,Employees!$G:$G)/12)+(SUMIF('Other Expenses'!$B:$B,'Income Statement'!$B25,'Other Expenses'!$E:$E)/12) -> 130814.17 | J25: =(SUMIF(Employees!$B:$B,'Income Statement'!$B25,Employees!$G:$G)/12)+(SUMIF('Other Expenses'!$B:$B,'Income Statement'!$B25,'Other Expenses'!$E:$E)/12) -> 130814.17 | ... N25: =(SUMIF(Employees!$B:$B,'Income Statement'!$B25,Employees!$G:$G)/12)+(SUMIF('Other Expenses'!$B:$B,'Income Statement'!$B25,'Other Expenses'!$E:$E)/12) -> 130814.17 | P25: =SUM(C25:N25) -> 1569770
B26: General & Administrative | C26: =(SUMIF(Employees!$B:$B,'Income Statement'!$B26,Employees!$G:$G)/12)+(SUMIF('Other Expenses'!$B:$B,'Income Statement'!$B26,'Other Expenses'!$E:$E)/12) -> 135691.67 | D26: =(SUMIF(Employees!$B:$B,'Income Statement'!$B26,Employees!$G:$G)/12)+(SUMIF('Other Expenses'!$B:$B,'Income Statement'!$B26,'Other Expenses'!$E:$E)/12) -> 135691.67 | E26: =(SUMIF(Employees!$B:$B,'Income Statement'!$B26,Employees!$G:$G)/12)+(SUMIF('Other Expenses'!$B:$B,'Income Statement'!$B26,'Other Expenses'!$E:$E)/12) -> 135691.67 | F26: =(SUMIF(Employees!$B:$B,'Income Statement'!$B26,Employees!$G:$G)/12)+(SUMIF('Other Expenses'!$B:$B,'Income Statement'!$B26,'Other Expenses'!$E:$E)/12) -> 135691.67 | G26: =(SUMIF(Employees!$B:$B,'Income Statement'!$B26,Employees!$G:$G)/12)+(SUMIF('Other Expenses'!$B:$B,'Income Statement'!$B26,'Other Expenses'!$E:$E)/12) -> 135691.67 | H26: =(SUMIF(Employees!$B:$B,'Income Statement'!$B26,Employees!$G:$G)/12)+(SUMIF('Other Expenses'!$B:$B,'Income Statement'!$B26,'Other Expenses'!$E:$E)/12) -> 135691.67 | I26: =(SUMIF(Employees!$B:$B,'Income Statement'!$B26,Employees!$G:$G)/12)+(SUMIF('Other Expenses'!$B:$B,'Income Statement'!$B26,'Other Expenses'!$E:$E)/12) -> 135691.67 | J26: =(SUMIF(Employees!$B:$B,'Income Statement'!$B26,Employees!$G:$G)/12)+(SUMIF('Other Expenses'!$B:$B,'Income Statement'!$B26,'Other Expenses'!$E:$E)/12) -> 135691.67 | ... N26: =(SUMIF(Employees!$B:$B,'Income Statement'!$B26,Employees!$G:$G)/12)+(SUMIF('Other Expenses'!$B:$B,'Income Statement'!$B26,'Other Expenses'!$E:$E)/12) -> 135691.67 | P26: =SUM(C26:N26) -> 1628300
B27: Total Operating Expenses | C27: =SUM(C23:C26) -> 429718.33 | D27: =SUM(D23:D26) -> 429718.33 | E27: =SUM(E23:E26) -> 429718.33 | F27: =SUM(F23:F26) -> 429718.33 | G27: =SUM(G23:G26) -> 429718.33 | H27: =SUM(H23:H26) -> 429718.33 | I27: =SUM(I23:I26) -> 429718.33 | J27: =SUM(J23:J26) -> 429718.33 | ... N27: =SUM(N23:N26) -> 429718.33 | P27: =SUM(P23:P26) -> 5156620
B29: EBITDA | C29: =C19-C27 -> -230364.17 | D29: =D19-D27 -> -154364.17 | E29: =E19-E27 -> 23444.833 | F29: =F19-F27 -> 84571.103 | G29: =G19-G27 -> 173315 | H29: =H19-H27 -> 316227.31 | I29: =I19-I27 -> 420390.44 | J29: =J19-J27 -> 520299.1 | ... N29: =N19-N27 -> 1067501.4 | P29: =P19-P27 -> 4573993.6
B34: Total Addressable Market (TAM)
B35: Average Revenue Per Unit | C35: ='Revenue Build'!P20 -> 41772.028
B36: TAM | C36: 26000
B37: Total Addressable Market (TAM) | C37: =IFERROR(C35*C36,"n/a") -> 1.0860727e+09

Sheet Revenue Build
A1: Revenue Build:
B3: Revenue | C3: 46023 | D3: =EOMONTH(C3,1) -> 46081 | E3: =EOMONTH(D3,1) -> 46112 | F3: =EOMONTH(E3,1) -> 46142 | G3: =EOMONTH(F3,1) -> 46173 | H3: =EOMONTH(G3,1) -> 46203 | I3: =EOMONTH(H3,1) -> 46234 | J3: =EOMONTH(I3,1) -> 46265 | K3: =EOMONTH(J3,1) -> 46295 | ... N3: =EOMONTH(M3,1) -> 46387 | P3: Total
B4: NEW CUSTOMERS:
B5: New Units Sold | C5: 0 | D5: 0 | E5: 2 | F5: 2 | G5: 2 | H5: 3 | I5: 3 | J5: 3 | K5: 4 | L5: 4 | M5: 4 | N5: 5 | P5: =SUM(C5:N5) -> 32
B6: Price per Unit | C6: 40000 | D6: =C6*(1+D7) -> 40000 | E6: =D6*(1+E7) -> 40400 | F6: =E6*(1+F7) -> 40804 | G6: =F6*(1+G7) -> 41212.04 | H6: =G6*(1+H7) -> 42036.281 | I6: =H6*(1+I7) -> 42877.006 | J6: =I6*(1+J7) -> 44163.317 | K6: =J6*(1+K7) -> 44163.317 | ... N6: =M6*(1+N7) -> 44163.317
B7: Price Increase % | D7: 0 | E7: 0.01 | F7: 0.01 | G7: 0.01 | H7: 0.02 | I7: 0.02 | J7: 0.03 | K7: 0 | L7: 0 | M7: 0 | N7: 0
B8: New Software Revenue | C8: =C5*C6 -> 0 | D8: =D5*D6 -> 0 | E8: =E5*E6 -> 80800 | F8: =F5*F6 -> 81608 | G8: =G5*G6 -> 82424.08 | H8: =H5*H6 -> 126108.84 | I8: =I5*I6 -> 128631.02 | J8: =J5*J6 -> 132489.95 | ... N8: =N5*N6 -> 220816.58 | P8: =SUM(C8:N8) -> 1382838.3
B10: EXISTING CUSTOMERS:
B11: Existing Customers Units | C11: 10 | D11: 12 | E11: 14 | F11: 16 | G11: 18 | H11: 20 | I11: 22 | J11: 24 | K11: 26 | L11: 28 | M11: 30 | N11: 32 | P11: =SUM(C11:N11) -> 252
B12: Avg Revenue per Unit | C12: =40000*(1+C13) -> 40000 | D12: =C12*(1+D13) -> 40000 | E12: =D12*(1+E13) -> 40000 | F12: =E12*(1+F13) -> 40000 | G12: =F12*(1+G13) -> 40000 | H12: =G12*(1+H13) -> 40800 | I12: =H12*(1+I13) -> 41616 | J12: =I12*(1+J13) -> 42448.32 | K12: =J12*(1+K13) -> 43297.286 | ... N12: =M12*(1+N13) -> 45947.427
B13: Renewal Increase % | D13: 0 | E13: 0 | F13: 0 | G13: 0 | H13: 0.02 | I13: 0.02 | J13: 0.02 | K13: 0.02 | L13: 0.02 | M13: 0.02 | N13: 0.02
B14: Existing Software Revenue | C14: =C11*C12 -> 400000 | D14: =D11*D12 -> 480000 | E14: =E11*E12 -> 560000 | F14: =F11*F12 -> 640000 | G14: =G11*G12 -> 720000 | H14: =H11*H12 -> 816000 | I14: =I11*I12 -> 915552 | J14: =J11*J12 -> 1018759.7 | ... N14: =N11*N12 -> 1470317.7 | P14: =SUM(C14:N14) -> 10734324
B16: Churn Rate | C16: 0.02 | D16: 0.025 | E16: 0.01 | F16: 0.04 | G16: 0.025 | H16: 0.025 | I16: 0.02 | J16: 0.025 | K16: 0.025 | L16: 0.04 | M16: 0.01 | N16: 0.02
B17: Churn $ | C17: =-C14*C16 -> -8000 | D17: =-D14*D16 -> -12000 | E17: =-E14*E16 -> -5600 | F17: =-F14*F16 -> -25600 | G17: =-G14*G16 -> -18000 | H17: =-H14*H16 -> -20400 | I17: =-I14*I16 -> -18311.04 | J17: =-J14*J16 -> -25468.992 | ... N17: =-N14*N16 -> -29406.353 | P17: =SUM(C17:N17) -> -253906.39
B19: Total Software Revenue | C19: =C17+C14+C8 -> 392000 | D19: =D17+D14+D8 -> 468000 | E19: =E17+E14+E8 -> 635200 | F19: =F17+F14+F8 -> 696008 | G19: =G17+G14+G8 -> 784424.08 | H19: =H17+H14+H8 -> 921708.84 | I19: =I17+I14+I8 -> 1025872 | J19: =J17+J14+J8 -> 1125780.6 | ... N19: =N17+N14+N8 -> 1661727.9 | P19: =P17+P14+P8 -> 11863256
B20: Avg Revenue per Unit (ARPU) | C20: =IFERROR(C19/(C5+C11),"n/a") -> 39200 | D20: =IFERROR(D19/(D5+D11),"n/a") -> 39000 | E20: =IFERROR(E19/(E5+E11),"n/a") -> 39700 | F20: =IFERROR(F19/(F5+F11),"n/a") -> 38667.111 | G20: =IFERROR(G19/(G5+G11),"n/a") -> 39221.204 | H20: =IFERROR(H19/(H5+H11),"n/a") -> 40074.297 | I20: =IFERROR(I19/(I5+I11),"n/a") -> 41034.879 | J20: =IFERROR(J19/(J5+J11),"n/a") -> 41695.579 | ... N20: =IFERROR(N19/(N5+N11),"n/a") -> 44911.564 | P20: =IFERROR(P19/(P5+P11),"n/a") -> 41772.028
B22: Services Revenue
B23: Price per Unit | C23: 5000 | D23: =C23*(1+D24) -> 5150 | E23: =D23*(1+E24) -> 5304.5 | F23: =E23*(1+F24) -> 5463.635 | G23: =F23*(1+G24) -> 5627.5441 | H23: =G23*(1+H24) -> 5627.5441 | I23: =H23*(1+I24) -> 5627.5441 | J23: =I23*(1+J24) -> 5627.5441 | K23: =J23*(1+K24) -> 5627.5441 | ... N23: =M23*(1+N24) -> 5627.5441
B24: Price Increase % | D24: 0.03 | E24: 0.03 | F24: 0.03 | G24: 0.03 | H24: 0 | I24: 0 | J24: 0 | K24: 0 | L24: 0 | M24: 0 | N24: 0
B25: Total Services Revenue | C25: =C5*C23 -> 0 | D25: =D5*D23 -> 0 | E25: =E5*E23 -> 10609 | F25: =F5*F23 -> 10927.27 | G25: =G5*G23 -> 11255.088 | H25: =H5*H23 -> 16882.632 | I25: =I5*I23 -> 16882.632 | J25: =J5*J23 -> 16882.632 | ... N25: =N5*N23 -> 28137.72 | P25: =SUM(C25:N25) -> 179107.5
B27: Total Revenue | C27: =C25+C19 -> 392000 | D27: =D25+D19 -> 468000 | E27: =E25+E19 -> 645809 | F27: =F25+F19 -> 706935.27 | G27: =G25+G19 -> 795679.17 | H27: =H25+H19 -> 938591.47 | I27: =I25+I19 -> 1042754.6 | J27: =J25+J19 -> 1142663.3 | ... N27: =N25+N19 -> 1689865.6 | P27: =P25+P19 -> 12042364

Sheet Employees
A1: Add details for team members including job title, annual salary, bonus %, and benefits % in to columns C, D, E and F. The annual cost will calculate automatically.
M3: Valid Categories (IS mapping)
A4: Department | B4: Category | C4: Job Title | D4: Annual Salary | E4: Bonus % | F4: Benefits % | G4: Annual Cost | M4: Cost of Sales - Software
A5: Support | B5: Cost of Sales - Software | C5: Support Manager | D5: 95000 | E5: 0.12 | F5: 0.18 | G5: =(D5*E5)+(D5*F5)+D5 -> 123500 | M5: Cost of Sales - Services
A6: Support | B6: Cost of Sales - Software | C6: Sr. Support Engineer | D6: 85000 | E6: 0.1 | F6: 0.18 | G6: =(D6*E6)+(D6*F6)+D6 -> 108800 | J6: Department Totals | M6: Sales
A7: Support | B7: Cost of Sales - Software | C7: Support Engineer | D7: 72000 | E7: 0.11 | F7: 0.18 | G7: =(D7*E7)+(D7*F7)+D7 -> 92880 | J7: Support | K7: =SUMIF($A:$A,$J7,$G:$G) -> 624110 | M7: Marketing
A8: Support | B8: Cost of Sales - Software | C8: Support Specialist II | D8: 65000 | E8: 0.09 | F8: 0.18 | G8: =(D8*E8)+(D8*F8)+D8 -> 82550 | J8: CET | K8: =SUMIF($A:$A,$J8,$G:$G) -> 607550 | M8: General & Administrative
A9: Support | B9: Cost of Sales - Software | C9: Support Specialist I | D9: 62000 | E9: 0.07 | F9: 0.18 | G9: =(D9*E9)+(D9*F9)+D9 -> 77500 | J9: Professional Services | K9: =SUMIF($A:$A,$J9,$G:$G) -> 908090 | M9: Engineering and Product
A10: Support | B10: Cost of Sales - Software | C10: Help Desk Analyst | D10: 57000 | E10: 0.06 | F10: 0.18 | G10: =(D10*E10)+(D10*F10)+D10 -> 70680 | J10: Sales | K10: =SUMIF($A:$A,$J10,$G:$G) -> 926050
A11: Support | B11: Cost of Sales - Software | C11: Customer Support Rep. | D11: 55000 | E11: 0.06 | F11: 0.18 | G11: =(D11*E11)+(D11*F11)+D11 -> 68200 | J11: Marketing | K11: =SUMIF($A:$A,$J11,$G:$G) -> 867500
A12: CET | B12: Cost of Sales - Software | C12: CET Manager | D12: 95000 | E12: 0.1 | F12: 0.18 | G12: =(D12*E12)+(D12*F12)+D12 -> 121600 | J12: General & Administrative | K12: =SUMIF($A:$A,$J12,$G:$G) -> 1373800
A13: CET | B13: Cost of Sales - Software | C13: Sr. Customer Enablement Specialist | D13: 82000 | E13: 0.08 | F13: 0.18 | G13: =(D13*E13)+(D13*F13)+D13 -> 103320 | J13: Engineering and Product | K13: =SUMIF($A:$A,$J13,$G:$G) -> 1569770
A14: CET | B14: Cost of Sales - Software | C14: Customer Enablement Specialist II | D14: 68000 | E14: 0.06 | F14: 0.18 | G14: =(D14*E14)+(D14*F14)+D14 -> 84320
A15: CET | B15: Cost of Sales - Software | C15: Customer Enablement Specialist I | D15: 65000 | E15: 0.06 | F15: 0.18 | G15: =(D15*E15)+(D15*F15)+D15 -> 80600
A16: CET | B16: Cost of Sales - Software | C16: Onboarding Specialist | D16: 60000 | E16: 0.05 | F16: 0.18 | G16: =(D16*E16)+(D16*F16)+D16 -> 73800
A17: CET | B17: Cost of Sales - Software | C17: Training and Adoption Specialist | D17: 62000 | E17: 0.05 | F17: 0.18 | G17: =(D17*E17)+(D17*F17)+D17 -> 76260
A18: CET | B18: Cost of Sales - Software | C18: Customer Enablement Coordinator | D18: 55000 | E18: 0.05 | F18: 0.18 | G18: =(D18*E18)+(D18*F18)+D18 -> 67650
A19: Professional Services | B19: Cost of Sales - Services | C19: Director of Professional Services | D19: 135000 | E19: 0.15 | F19: 0.18 | G19: =(D19*E19)+(D19*F19)+D19 -> 179550
A20: Professional Services | B20: Cost of Sales - Services | C20: Sr. Implementation Consultant | D20: 110000 | E20: 0.1 | F20: 0.18 | G20: =(D20*E20)+(D20*F20)+D20 -> 140800
A21: Professional Services | B21: Cost of Sales - Services | C21: Implementation Consultant II | D21: 85000 | E21: 0.08 | F21: 0.18 | G21: =(D21*E21)+(D21*F21)+D21 -> 107100
A22: Professional Services | B22: Cost of Sales - Services | C22: Implementation Consultant I | D22: 82000 | E22: 0.08 | F22: 0.18 | G22: =(D22*E22)+(D22*F22)+D22 -> 103320
A23: Professional Services | B23: Cost of Sales - Services | C23: Solutions Architect | D23: 118000 | E23: 0.08 | F23: 0.18 | G23: =(D23*E23)+(D23*F23)+D23 -> 148680
A24: Professional Services | B24: Cost of Sales - Services | C24: Project Manager | D24: 92000 | E24: 0.1 | F24: 0.18 | G24: =(D24*E24)+(D24*F24)+D24 -> 117760
A25: Professional Services | B25: Cost of Sales - Services | C25: Technical Consultant | D25: 88000 | E25: 0.08 | F25: 0.18 | G25: =(D25*E25)+(D25*F25)+D25 -> 110880
... A57: Engineering and Product | B57: Engineering and Product | C57: Prodcut Designer | D57: 92000 | E57: 0.08 | F57: 0.18 | G57: =(D57*E57)+(D57*F57)+D57 -> 115920

Sheet Other Expenses
A1: Add details for expenses in to columns C and D and include in annual cost in column E
A4: Department | B4: Category | C4: Expense Category | D4: Description/Vendor | E4: Annual Cost
A5: Support | B5: Cost of Sales - Software | C5: Software Tools & Licensing | D5: Jira | E5: 5500
A6: Support | B6: Cost of Sales - Software | C6: Cloud Hosting & Infrastructure | D6: AWS Support Environment | E6: 12000 | H6: Department Totals
A7: Support | B7: Cost of Sales - Software | C7: Training & Certification | D7: Vendor Product Training | E7: 6500 | H7: Support | I7: =SUMIF($A:$A,$H7,$E:$E) -> 52000
A8: Support | B8: Cost of Sales - Software | C8: Travel & Client Site Visits | D8: Airfare, Lodging, Mileage | E8: 11000 | H8: CET | I8: =SUMIF($A:$A,$H8,$E:$E) -> 58500
A9: Support | B9: Cost of Sales - Software | C9: Equipment & Hardware | D9: Laptops, Headsets, Monitors | E9: 9000 | H9: Professional Services | I9: =SUMIF($A:$A,$H9,$E:$E) -> 61500
A10: Support | B10: Cost of Sales - Software | C10: Recruiting & Onboarding | D10: Job Postings & Background Checks | E10: 5500 | H10: Sales | I10: =SUMIF($A:$A,$H10,$E:$E) -> 71000
A11: Support | B11: Cost of Sales - Software | C11: Office Supplies & Misc. | D11: General Departmnet Supplies | E11: 2500 | H11: Marketing | I11: =SUMIF($A:$A,$H11,$E:$E) -> 94000
A12: CET | B12: Cost of Sales - Software | C12: Customer Enablement Platform | D12: LMS & Training Software | E12: 20000 | H12: General & Administrative | I12: =SUMIF($A:$A,$H12,$E:$E) -> 254500
A13: CET | B13: Cost of Sales - Software | C13: Travel & Onsite Enablement Visits | D13: Airfare & Lodging | E13: 9000 | H13: Engineering and Product | I13: =SUMIF($A:$A,$H13,$E:$E) -> 0
A14: CET | B14: Cost of Sales - Software | C14: Training Materials & Content Development | D14: Freelance Instructional Designer | E14: 8500
A15: CET | B15: Cost of Sales - Software | C15: Equipment & Hardware | D15: Laptops & Presentation Equipment | E15: 7500
A16: CET | B16: Cost of Sales - Software | C16: Software Tools & Licensing | D16: Zoom & Miro | E16: 5500
A17: CET | B17: Cost of Sales - Software | C17: Recruiting & Onboarding | D17: Job Postings & Assessments | E17: 5500
A18: CET | B18: Cost of Sales - Software | C18: Office Supplies & Misc. | D18: General Deparment Supplies | E18: 2500
A19: Professional Services | B19: Cost of Sales - Services | C19: Project Management Software | D19: Smartsheet License | E19: 11000
A20: Professional Services | B20: Cost of Sales - Services | C20: Tracel & Client Implementation Visits | D20: Airfare & Lodging | E20: 9000
A21: Professional Services | B21: Cost of Sales - Services | C21: Subcontractor & Consulting Fees | D21: Overflow Implementation Support | E21: 15000
A22: Professional Services | B22: Cost of Sales - Services | C22: Equipment & Hardware | D22: Laptops & Peripherals | E22: 9000
A23: Professional Services | B23: Cost of Sales - Services | C23: Training & Certification | D23: Technical Product Certification | E23: 6500
A24: Professional Services | B24: Cost of Sales - Services | C24: Software Tools & Licensing | D24: Technical Documentation Tools | E24: 5500
A25: Professional Services | B25: Cost of Sales - Services | C25: Recruiting & Onboarding | D25: Job Postings & Background Checks | E25: 5500
... A47: General & Administrative | B47: General & Administrative | C47: Office Supplies & Misc. | D47: General Department Supplies | E47: 2500
A48: Engineering and Product | B48: Engineering and Product | C48: Software Tools & Licensing | E48: 0
A49: Engineering and Product | B49: Engineering and Product | C49: Hardware | E49: 0
A50: Engineering and Product | B50: Engineering and Product | C50: Training & Certification | E50: 0
A51: Engineering and Product | B51: Engineering and Product | C51: Cloud Hosting & Infrastructure | E51: 0
A52: Engineering and Product | B52: Engineering and Product | E52: 0
A53: Engineering and Product | B53: Engineering and Product | E53: 0
A54: Engineering and Product | B54: Engineering and Product | E54: 0
A55: Engineering and Product | B55: Engineering and Product | E55: 0
A56: Engineering and Product | B56: Engineering and Product | E56: 0
A57: Engineering and Product | B57: Engineering and Product | E57: 0

Sheet Metrics
A4: Gross Margin
A6: CAC
A8: Average Revenue Per Customer
A10: Monthly Recurring Revenue (MRR)
A12: Annual Recurring Revenue (ARR)
A14: Churn
